pointr_cloud_v8_mcp_server/PointrAgent.py
pointr_cloud_v8_mcp_server/__init__.py
pointr_cloud_v8_mcp_server/__main__.py
pointr_cloud_v8_mcp_server/app.py
pointr_cloud_v8_mcp_server/server.py
pointr_cloud_v8_mcp_server-0.1.5.dist-info/licenses/LICENSE
pointr_cloud_v8_mcp_server-0.1.5.dist-info/METADATA
pointr_cloud_v8_mcp_server-0.1.5.dist-info/WHEEL
pointr_cloud_v8_mcp_server-0.1.5.dist-info/entry_points.txt
pointr_cloud_v8_mcp_server-0.1.5.dist-info/top_level.txt
pointr_cloud_v8_mcp_server-0.1.5.dist-info/RECORD
