Metadata-Version: 2.4
Name: pointr-cloud-v8-mcp-server
Version: 0.1.5
Summary: Indoor location assistant using Pointr MCP server to provide QR code navigation for venues.
Author-email: Pointr Software Delivery Team <support@pointr.tech>
License-Expression: MIT
Project-URL: homepage, https://pypi.org/project/pointr-cloud-v8-mcp-server/
Requires-Python: >=3.13
License-File: LICENSE
Requires-Dist: python-dotenv
Requires-Dist: openai-agents
Dynamic: license-file
